{
  "en": [
    {
      "visitnumber": 10,
      "date": "10/1/2025",
      "time": "10:30 AM",
      "servicename": "Professional Accreditation for Engineers",
      "employeename": "Khaled Abdullah Al-Masabi",
      "servicerating": 5,
      "servicedescription": "This text is a placeholder example that can be replaced with actual content in the same space.",
      "employeerating": 4,
      "employeedescription": "This text is a placeholder example that can be replaced with actual content in the same space."
    },
    {
      "visitnumber": 10,
      "date": "10/1/2025",
      "time": "10:30 AM",
      "servicename": "Professional Accreditation for Engineers",
      "employeename": "Khaled Abdullah Al-Masabi",
      "servicerating": 3,
      "servicedescription": "This text is a placeholder example that can be replaced with actual content in the same space.",
      "employeerating": 2,
      "employeedescription": "This text is a placeholder example that can be replaced with actual content in the same space."
    },
    {
      "visitnumber": 10,
      "date": "10/1/2025",
      "time": "10:30 AM",
      "servicename": "Professional Accreditation for Engineers",
      "employeename": "Khaled Abdullah Al-Masabi",
      "servicerating": 5,
      "servicedescription": "This text is a placeholder example that can be replaced with actual content in the same space.",
      "employeerating": 4,
      "employeedescription": "This text is a placeholder example that can be replaced with actual content in the same space."
    }
  ],
  "ar": [
    {
      "visitnumber": 10,
      "date": " 10/1/2025",
      "time": "10:30 صباحا",
      "servicename": "الاعتماد المهني للمهندسين",
      "employeename": "ا خالد عبدالله المصعبي",
      "servicerating": 2,
      "servicedescription": "هذا النص هو مثال لنص يمكن أن يستبدل في نفس المساحة",
      "employeerating": 5,
      "employeedescription": "هذا النص هو مثال لنص يمكن أن يستبدل في نفس المساحة"
    },
    {
      "visitnumber": 10,
      "date": " 10/1/2025",
      "time": "10:30 صباحا",
      "servicename": "الاعتماد المهني للمهندسين",
      "employeename": "ا خالد عبدالله المصعبي",
      "servicerating": 4,
      "servicedescription": "هذا النص هو مثال لنص يمكن أن يستبدل في نفس المساحة",
      "employeerating": 3,
      "employeedescription": "هذا النص هو مثال لنص يمكن أن يستبدل في نفس المساحة"
    },
    {
      "visitnumber": 10,
      "date": " 10/1/2025",
      "time": "10:30 صباحا",
      "servicename": "الاعتماد المهني للمهندسين",
      "employeename": "ا خالد عبدالله المصعبي",
      "servicerating": 5,
      "servicedescription": "هذا النص هو مثال لنص يمكن أن يستبدل في نفس المساحة",
      "employeerating": 4,
      "employeedescription": "هذا النص هو مثال لنص يمكن أن يستبدل في نفس المساحة"
    },
    {
      "visitnumber": 10,
      "date": " 10/1/2025",
      "time": "10:30 صباحا",
      "servicename": "الاعتماد المهني للمهندسين",
      "employeename": "ا خالد عبدالله المصعبي",
      "servicerating": 5,
      "servicedescription": "هذا النص هو مثال لنص يمكن أن يستبدل في نفس المساحة",
      "employeerating": 4,
      "employeedescription": "هذا النص هو مثال لنص يمكن أن يستبدل في نفس المساحة"
    },
    {
      "visitnumber": 10,
      "date": " 10/1/2025",
      "time": "10:30 صباحا",
      "servicename": "الاعتماد المهني للمهندسين",
      "employeename": "ا خالد عبدالله المصعبي",
      "servicerating": 5,
      "servicedescription": "هذا النص هو مثال لنص يمكن أن يستبدل في نفس المساحة",
      "employeerating": 4,
      "employeedescription": "هذا النص هو مثال لنص يمكن أن يستبدل في نفس المساحة"
    }
  ]
}
